pandarm/__init__.py
pandarm/cyaccess.cp314-win32.pyd
pandarm/network.py
pandarm/testing.py
pandarm/utils.py
pandarm/loaders/__init__.py
pandarm/loaders/osm.py
pandarm/loaders/pandash5.py
pandarm-0.0.4.dist-info/licenses/LICENSE
src/accessibility.cpp
src/accessibility.h
src/cyaccess.pyx
src/graphalg.cpp
src/graphalg.h
src/shared.h
src/contraction_hierarchies/Makefile
src/contraction_hierarchies/src/BasicDefinitions.h
src/contraction_hierarchies/src/libch.cpp
src/contraction_hierarchies/src/libch.h
src/contraction_hierarchies/src/Contractor/ContractionCleanup.h
src/contraction_hierarchies/src/Contractor/Contractor.h
src/contraction_hierarchies/src/DataStructures/BinaryHeap.h
src/contraction_hierarchies/src/DataStructures/DynamicGraph.h
src/contraction_hierarchies/src/DataStructures/Percent.h
src/contraction_hierarchies/src/DataStructures/SimpleCHQuery.h
src/contraction_hierarchies/src/DataStructures/StaticGraph.h
src/contraction_hierarchies/src/POIIndex/POIIndex.h
src/contraction_hierarchies/src/Util/HyperThreading.h
pandarm-0.0.4.dist-info/METADATA
pandarm-0.0.4.dist-info/WHEEL
pandarm-0.0.4.dist-info/top_level.txt
pandarm-0.0.4.dist-info/RECORD
