Metadata-Version: 2.4
Name: pandarm
Version: 0.0.4
Summary: The Pandas Routing Machine
Project-URL: Home, https://github.com/oturns/pandarm/
Project-URL: Repository, https://github.com/oturns/pandarm
Keywords: routing, network analysis, accessibility, shortest paths, isochrone
Classifier: Programming Language :: Python :: 3
Classifier: License :: OSI Approved :: GNU Affero General Public License v3
Requires-Python: >=3.10
License-File: LICENSE
Requires-Dist: geopandas>=1.1
Requires-Dist: numpy>=1.26
Requires-Dist: pandas>=2.2
Requires-Dist: scikit-learn>=1.4
Requires-Dist: tables>=3.10
Provides-Extra: plus
Requires-Dist: osmnx>=2.0; extra == "plus"
Provides-Extra: dev
Requires-Dist: codecov; extra == "dev"
Requires-Dist: pre-commit; extra == "dev"
Requires-Dist: pytest; extra == "dev"
Requires-Dist: pytest-cov; extra == "dev"
Provides-Extra: docs
Requires-Dist: myst-parser; extra == "docs"
Requires-Dist: nbsphinx; extra == "docs"
Requires-Dist: numpydoc; extra == "docs"
Requires-Dist: sphinx; extra == "docs"
Requires-Dist: sphinxcontrib-bibtex; extra == "docs"
Requires-Dist: sphinx_bootstrap_theme; extra == "docs"
Provides-Extra: all
Requires-Dist: pandarm[dev,docs,plus]; extra == "all"
Dynamic: license-file
